pgcs/__init__.py
pgcs/custom_select.py
pgcs/file_system/__init__.py
pgcs/file_system/base.py
pgcs/file_system/entries.py
pgcs/main.py
pgcs/preferences.py
pgcs/utils.py
pgcs-0.1.2.dist-info/LICENSE
pgcs-0.1.2.dist-info/METADATA
pgcs-0.1.2.dist-info/WHEEL
pgcs-0.1.2.dist-info/entry_points.txt
pgcs-0.1.2.dist-info/RECORD
